altxria/hermes/__init__.py
altxria/hermes/cli.py
altxria/hermes/config.py
altxria/hermes/database.py
altxria/hermes/exceptions.py
altxria/hermes/fields.py
altxria/hermes/migrations.py
altxria/hermes/model.py
altxria/hermes/query_builder.py
altxria/hermes/relations.py
hermes_orm-0.1.7.dist-info/LICENSE
hermes_orm-0.1.7.dist-info/METADATA
hermes_orm-0.1.7.dist-info/WHEEL
hermes_orm-0.1.7.dist-info/entry_points.txt
hermes_orm-0.1.7.dist-info/top_level.txt
hermes_orm-0.1.7.dist-info/RECORD
