Metadata-Version: 2.1
Name: hermes-orm
Version: 0.1.7
Summary: A high-performance ORM for Python with support for migrations, relations, and caching.
Home-page: https://github.com/altxriainc/hermes
Author: Altxria Inc.
Author-email: company@altxria.com
License: CC BY-ND 4.0
Project-URL: Bug Tracker, https://github.com/altxriainc/hermes/issues
Project-URL: Documentation, https://github.com/altxriainc/hermes/wiki
Project-URL: Source Code, https://github.com/altxriainc/hermes
Keywords: ORM Python SQL migrations relations caching
Classifier: Development Status :: 4 - Beta
Classifier: Intended Audience :: Developers
Classifier: License :: OSI Approved :: MIT License
Classifier: Programming Language :: Python :: 3
Classifier: Programming Language :: Python :: 3.7
Classifier: Programming Language :: Python :: 3.8
Classifier: Programming Language :: Python :: 3.9
Classifier: Programming Language :: Python :: 3.10
Classifier: Programming Language :: Python :: 3.11
Classifier: Operating System :: OS Independent
Requires-Python: >=3.7
License-File: LICENSE
Requires-Dist: click>=8.0
Requires-Dist: aiosqlite>=0.17
Provides-Extra: dev
Requires-Dist: pytest>=7.0; extra == "dev"
Requires-Dist: black>=23.0; extra == "dev"
Requires-Dist: flake8>=6.0; extra == "dev"
